tsar/AR.py
tsar/__init__.py
tsar/autoregressive.py
tsar/autotune.py
tsar/baseline.py
tsar/data_reshape.py
tsar/gaussian_model.py
tsar/generate_data.py
tsar/greedy_grid_search.py
tsar/linear_algebra.py
tsar/new_linear_algebra.py
tsar/non_par_baseline.py
tsar/test_AR.py
tsar/test_baseline.py
tsar/test_grid_search.py
tsar/test_linear_algebra.py
tsar/test_tsar.py
tsar/tsar.py
tsar/utils.py
tsar-0.9.1.dist-info/LICENSE
tsar-0.9.1.dist-info/METADATA
tsar-0.9.1.dist-info/WHEEL
tsar-0.9.1.dist-info/top_level.txt
tsar-0.9.1.dist-info/RECORD
