Metadata-Version: 2.1
Name: tsar
Version: 0.9.1
Summary: Time series auto-regressor.
Home-page: UNKNOWN
Author: Enzo Busseti
Author-email: UNKNOWN
License: GPLv3+
Platform: UNKNOWN
Requires-Dist: scipy (>=1.3.1)
Requires-Dist: numpy (>=1.17.3)
Requires-Dist: numba (>=0.46.0)
Requires-Dist: pandas (>=0.25.3)
Requires-Dist: lrbd
